{"cameraMode":{"drawMode":0,"name":"Shaded","section":"Shading Mode"},"sceneLighting":false,"audioPlay":false,"sceneViewState":{"m_AlwaysRefresh":false,"showFog":true,"showSkybox":false,"showFlares":true,"showImageEffects":true,"showParticleSystems":true,"showVisualEffectGraphs":true,"m_FxEnabled":true},"in2DMode":false,"pivot":{"x":-63.61205291748047,"y":5.704241752624512,"z":63.28203582763672},"rotation":{"x":-0.19667260348796845,"y":0.6443397402763367,"z":-0.1763487011194229,"w":-0.7177680134773254},"size":1.0024945735931397,"orthographic":false}