{"cameraMode":{"drawMode":0,"name":"Shaded","section":"Shading Mode"},"sceneLighting":true,"audioPlay":false,"sceneViewState":{"m_AlwaysRefresh":false,"showFog":true,"showSkybox":true,"showFlares":true,"showImageEffects":true,"showParticleSystems":true,"showVisualEffectGraphs":true,"m_FxEnabled":true},"in2DMode":false,"pivot":{"x":32.330787658691409,"y":2.313441514968872,"z":2.9392619132995607},"rotation":{"x":0.487394779920578,"y":-0.5124559998512268,"z":0.5008187890052795,"w":0.4993675947189331},"size":1.2216732501983643,"orthographic":false}